 {"code":0,"data":{"list":[{"Flisten_count1":0,"Fupload_time":"2007-12-06 11:53:46","index":1,"isnew":0,"listenCount":0,"musicData":{"albumdesc":"《兄弟》电影主题曲","albumid":33445,"albummid":"003H8fyC2COWJ4","albumname":"Everyone Is No.1","alertid":21,"belongCD":18,"cdIdx":1,"interval":243,"isonly":1,"label":"4611686153727246337","msgid":14,"pay":{"payalbum":0,"payalbumprice":0,"paydownload":1,"payinfo":1,"payplay":0,"paytrackmouth":1,"paytrackprice":200,"timefree":0},"preview":{"trybegin":0,"tryend":0,"trysize":0},"rate":31,"singer":[{"id":163,"mid":"003aQYLo2x8izP","name":"刘德华"},{"id":143,"mid":"003Nz2So3XXYek","name":"陈奕迅"}],"size128":3896676,"size320":9719891,"size5_1":0,"sizeape":30987179,"sizeflac":31723597,"sizeogg":6265948,"songid":413859,"songmid":"002TrbOP1iPSDf","songname":"兄弟","songorig":"兄弟","songtype":0,"strMediaMid":"002TrbOP1iPSDf","stream":13,"switch":17413891,"type":0,"vid":"o0012p09dyw"},"playurl":"","price":320,"vid":{"Fmv_id":"200722","Fstatus":"1","Fvid":"o0012p09dyw"}},{"Flisten_count1":0,"Fupload_time":"2013-06-20 21:05:23","index":2,"isnew":0,"listenCount":0,"musicData":{"albumdesc":"《兄妹》粤语版|《冲上云霄》电影主题曲|《冲上云霄》电视剧主题曲","albumid":89544,"albummid":"003Hjc6L1WajuE","albumname":"Live For Today","alertid":21,"belongCD":11,"cdIdx":0,"interval":207,"isonly":1,"label":"5764607523038429186","msgid":14,"pay":{"payalbum":0,"payalbumprice":0,"paydownload":1,"payinfo":1,"payplay":0,"paytrackmouth":1,"paytrackprice":200,"timefree":0},"preview":{"trybegin":55890,"tryend":80819,"trysize":0},"rate":31,"singer":[{"id":143,"mid":"003Nz2So3XXYek","name":"陈奕迅"}],"size128":3326755,"size320":8316561,"size5_1":0,"sizeape":20651965,"sizeflac":20904439,"sizeogg":4557254,"songid":4907829,"songmid":"002sNbXT088Yuy","songname":"岁月如歌","songorig":"岁月如歌","songtype":0,"strMediaMid":"002sNbXT088Yuy","stream":13,"switch":17413891,"type":0,"vid":"c0016w81a3i"},"playurl":"","price":320,"vid":{"Fmv_id":"308219","Fstatus":"1","Fvid":"c0016w81a3i"}},{"Flisten_count1":0,"Fupload_time":"2005-02-28 11:00:13","index":3,"isnew":0,"listenCount":0,"musicData":{"albumdesc":"","albumid":743,"albummid":"004E0Y0A0R8FYZ","albumname":"Special Thanks To…","alertid":21,"belongCD":3,"cdIdx":0,"interval":263,"isonly":1,"label":"5764607523034234881","msgid":14,"pay":{"payalbum":0,"payalbumprice":0,"paydownload":1,"payinfo":1,"payplay":0,"paytrackmouth":1,"paytrackprice":200,"timefree":0},"preview":{"trybegin":85581,"tryend":114623,"trysize":0},"rate":31,"singer":[{"id":143,"mid":"003Nz2So3XXYek","name":"陈奕迅"}],"size128":4219681,"size320":10423167,"size5_1":0,"sizeape":29634311,"sizeflac":30725455,"sizeogg":5813965,"songid":8770,"songmid":"003itfg21R0Hb5","songname":"谢谢侬","songorig":"谢谢侬","songtype":0,"strMediaMid":"003itfg21R0Hb5","stream":13,"switch":17413891,"type":0,"vid":"Q0010WGYx1R"},"playurl":"","price":320,"vid":{"Fmv_id":"140638","Fstatus":"1","Fvid":"Q0010WGYx1R"}},{"Flisten_count1":0,"Fupload_time":"2012-04-10 16:04:23","index":4,"isnew":0,"listenCount":0,"musicData":{"albumdesc":"","albumid":7879,"albummid":"003J6fvc0bVJon","albumname":"U-87","alertid":21,"belongCD":6,"cdIdx":0,"interval":277,"isonly":1,"label":"4611686153727246338","msgid":14,"pay":{"payalbum":0,"payalbumprice":0,"paydownload":1,"payinfo":1,"payplay":0,"paytrackmouth":1,"paytrackprice":200,"timefree":0},"preview":{"trybegin":0,"tryend":0,"trysize":0},"rate":23,"singer":[{"id":143,"mid":"003Nz2So3XXYek","name":"陈奕迅"}],"size128":4433911,"size320":11084477,"size5_1":0,"sizeape":0,"sizeflac":32416001,"sizeogg":6327672,"songid":1251167,"songmid":"0029Zemv0kR1ur","songname":"葡萄成熟时","songorig":"葡萄成熟时","songtype":0,"strMediaMid":"004V8Yph2t2V7s","stream":13,"switch":17413891,"type":0,"vid":"q0010Lj82uC"},"playurl":"","price":320,"vid":{"Fmv_id":"140633","Fstatus":"1","Fvid":"q0010Lj82uC"}},{"Flisten_count1":0,"Fupload_time":"2010-06-29 15:31:30","index":5,"isnew":0,"listenCount":0,"musicData":{"albumdesc":"","albumid":58757,"albummid":"002gBayj0ZPoR0","albumname":"DUO 陈奕迅2010演唱会","alertid":21,"belongCD":6,"cdIdx":0,"interval":336,"isonly":1,"label":"4611686153727246338","msgid":14,"pay":{"payalbum":0,"payalbumprice":0,"paydownload":1,"payinfo":1,"payplay":0,"paytrackmouth":1,"paytrackprice":200,"timefree":0},"preview":{"trybegin":0,"tryend":0,"trysize":0},"rate":23,"singer":[{"id":143,"mid":"003Nz2So3XXYek","name":"陈奕迅"}],"size128":5381438,"size320":13452819,"size5_1":0,"sizeape":0,"sizeflac":32535840,"sizeogg":7474516,"songid":694534,"songmid":"0002YUn010xKbf","songname":"约定 (Live)","songorig":"约定","songtype":0,"strMediaMid":"003WLeJu2t9NAu","stream":13,"switch":17413891,"type":0,"vid":"b00229hhw66"},"playurl":"","price":320,"vid":{"Fmv_id":"1085434","Fstatus":"1","Fvid":"b00229hhw66"}},{"Flisten_count1":0,"Fupload_time":"2013-06-06 20:34:20","index":6,"isnew":0,"listenCount":0,"musicData":{"albumdesc":"","albumid":89545,"albummid":"0032Q9j23dL9tw","albumname":"Third Encounter Live","alertid":21,"belongCD":17,"cdIdx":0,"interval":268,"isonly":1,"label":"4611686018435776514","msgid":14,"pay":{"payalbum":0,"payalbumprice":0,"paydownload":1,"payinfo":1,"payplay":0,"paytrackmouth":1,"paytrackprice":200,"timefree":0},"preview":{"trybegin":88990,"tryend":120840,"trysize":0},"rate":31,"singer":[{"id":143,"mid":"003Nz2So3XXYek","name":"陈奕迅"}],"size128":4301454,"size320":10753281,"size5_1":0,"sizeape":30264530,"sizeflac":30378780,"sizeogg":6033822,"songid":4829894,"songmid":"001Vjx3D3QwXp3","songname":"一生中最爱 (Live)","songorig":"一生中最爱","songtype":0,"strMediaMid":"001Vjx3D3QwXp3","stream":13,"switch":17413891,"type":0,"vid":"s00168l5s6e"},"playurl":"","price":320,"vid":{"Fmv_id":"329612","Fstatus":"1","Fvid":"s00168l5s6e"}},{"Flisten_count1":0,"Fupload_time":"2012-10-02 11:05:43","index":7,"isnew":0,"listenCount":0,"musicData":{"albumdesc":"","albumid":150188,"albummid":"0002FYdP4f5A2f","albumname":"Concert YY 黄伟文作品展 演唱会","alertid":11,"belongCD":26,"cdIdx":1,"interval":249,"isonly":0,"label":"4611686018435776514","msgid":0,"pay":{"payalbum":0,"payalbumprice":0,"paydownload":0,"payinfo":0,"payplay":0,"paytrackmouth":0,"paytrackprice":0,"timefree":0},"preview":{"trybegin":0,"tryend":0,"trysize":0},"rate":31,"singer":[{"id":143,"mid":"003Nz2So3XXYek","name":"陈奕迅"}],"size128":3992156,"size320":9979820,"size5_1":0,"sizeape":24395716,"sizeflac":24577014,"sizeogg":5687009,"songid":1923005,"songmid":"000lILzp2Y5dFW","songname":"倾城 (Live)","songorig":"倾城","songtype":0,"strMediaMid":"004bI4nQ1TWAE5","stream":13,"switch":3227447,"type":0,"vid":"s0019pgqxr4"},"playurl":"","price":320,"vid":{"Fmv_id":"647181","Fstatus":"1","Fvid":"s0019pgqxr4"}},{"Flisten_count1":0,"Fupload_time":"2012-04-10 15:07:59","index":8,"isnew":0,"listenCount":0,"musicData":{"albumdesc":"","albumid":68074,"albummid":"000Iv0BM0vOHkK","albumname":"Stranger Under My Skin","alertid":21,"belongCD":4,"cdIdx":0,"interval":278,"isonly":1,"label":"4611686018431582210","msgid":14,"pay":{"payalbum":0,"payalbumprice":0,"paydownload":1,"payinfo":1,"payplay":0,"paytrackmouth":1,"paytrackprice":200,"timefree":0},"preview":{"trybegin":0,"tryend":0,"trysize":0},"rate":23,"singer":[{"id":143,"mid":"003Nz2So3XXYek","name":"陈奕迅"}],"size128":4458600,"size320":11146156,"size5_1":0,"sizeape":0,"sizeflac":28342747,"sizeogg":6046394,"songid":1250812,"songmid":"000B9Nho3hgIY7","songname":"苦瓜","songorig":"苦瓜","songtype":0,"strMediaMid":"000mTVsb2RORKF","stream":13,"switch":17413891,"type":0,"vid":"f00117zjpge"},"playurl":"","price":320,"vid":{"Fmv_id":"148965","Fstatus":"1","Fvid":"f00117zjpge"}},{"Flisten_count1":0,"Fupload_time":"2013-06-20 21:05:22","index":9,"isnew":0,"listenCount":0,"musicData":{"albumdesc":"","albumid":89544,"albummid":"003Hjc6L1WajuE","albumname":"Live For Today","alertid":21,"belongCD":3,"cdIdx":0,"interval":232,"isonly":1,"label":"5764607523042623490","msgid":14,"pay":{"payalbum":0,"payalbumprice":0,"paydownload":1,"payinfo":1,"payplay":0,"paytrackmouth":1,"paytrackprice":200,"timefree":0},"preview":{"trybegin":0,"tryend":0,"trysize":0},"rate":31,"singer":[{"id":143,"mid":"003Nz2So3XXYek","name":"陈奕迅"}],"size128":3715457,"size320":9288316,"size5_1":0,"sizeape":25871037,"sizeflac":26016572,"sizeogg":5255010,"songid":4907821,"songmid":"000lVKbP3bCwxu","songname":"十面埋伏","songorig":"十面埋伏","songtype":0,"strMediaMid":"000lVKbP3bCwxu","stream":13,"switch":17413891,"type":0,"vid":"9HYLtinhojk"},"playurl":"","price":320,"vid":{"Fmv_id":"84581","Fstatus":"1","Fvid":"9HYLtinhojk"}},{"Flisten_count1":0,"Fupload_time":"2017-07-14 20:28:38","index":10,"isnew":0,"listenCount":0,"musicData":{"albumdesc":"","albumid":2163974,"albummid":"0047jGIX0ts8bA","albumname":"中国新歌声第二季 第1期","alertid":21,"belongCD":7,"cdIdx":0,"interval":177,"isonly":1,"label":"0","msgid":14,"pay":{"payalbum":0,"payalbumprice":0,"paydownload":1,"payinfo":1,"payplay":0,"paytrackmouth":1,"paytrackprice":200,"timefree":0},"preview":{"trybegin":0,"tryend":0,"trysize":0},"rate":31,"singer":[{"id":137,"mid":"003LCFXH0eodXv","name":"那英"},{"id":4558,"mid":"0025NhlN2yWrP4","name":"周杰伦"},{"id":4533,"mid":"003PxzeJ2YXXuu","name":"刘欢"},{"id":143,"mid":"003Nz2So3XXYek","name":"陈奕迅"}],"size128":2845680,"size320":7113554,"size5_1":0,"sizeape":20839859,"sizeflac":20909430,"sizeogg":3745915,"songid":203255244,"songmid":"0006JEJn3vGCu3","songname":"沧海一声笑 (Live)","songorig":"沧海一声笑","songtype":0,"strMediaMid":"0017Aiq80Jdn6s","stream":13,"switch":17409795,"type":0,"vid":""},"playurl":"","price":320,"vid":{"Fstatus":null}},{"Flisten_count1":0,"Fupload_time":"2012-04-10 11:37:48","index":11,"isnew":0,"listenCount":0,"musicData":{"albumdesc":"《好久不见》粤语版","albumid":51144,"albummid":"003nMzes28P7wv","albumname":"What's Going On…?","alertid":21,"belongCD":6,"cdIdx":0,"interval":249,"isonly":1,"label":"4611686153723052034","msgid":14,"pay":{"payalbum":0,"payalbumprice":0,"paydownload":1,"payinfo":1,"payplay":0,"paytrackmouth":1,"paytrackprice":200,"timefree":0},"preview":{"trybegin":0,"tryend":0,"trysize":0},"rate":23,"singer":[{"id":143,"mid":"003Nz2So3XXYek","name":"陈奕迅"}],"size128":3995913,"size320":9989448,"size5_1":0,"sizeape":0,"sizeflac":19944815,"sizeogg":5056832,"songid":1249551,"songmid":"001hgaJJ0XcjtR","songname":"不如不见","songorig":"不如不见","songtype":0,"strMediaMid":"001jiYOc0kDFRR","stream":13,"switch":17413891,"type":0,"vid":""},"playurl":"","price":320,"vid":{"Fstatus":null}},{"Flisten_count1":0,"Fupload_time":"2015-09-25 19:33:41","index":12,"isnew":0,"listenCount":0,"musicData":{"albumdesc":"","albumid":87048,"albummid":"003YQ8lP3NBXKl","albumname":"?","alertid":21,"belongCD":8,"cdIdx":0,"interval":240,"isonly":1,"label":"4611686153723052033","msgid":14,"pay":{"payalbum":0,"payalbumprice":0,"paydownload":1,"payinfo":1,"payplay":0,"paytrackmouth":1,"paytrackprice":200,"timefree":0},"preview":{"trybegin":71401,"tryend":117116,"trysize":0},"rate":31,"singer":[{"id":143,"mid":"003Nz2So3XXYek","name":"陈奕迅"}],"size128":3845830,"size320":9614040,"size5_1":0,"sizeape":26198824,"sizeflac":26380808,"sizeogg":5189666,"songid":104362682,"songmid":"001dOQx60k8FhC","songname":"内疚","songorig":"内疚","songtype":0,"strMediaMid":"001dOQx60k8FhC","stream":13,"switch":17413891,"type":0,"vid":"k0090OSAaO0"},"playurl":"","price":320,"vid":{"Fmv_id":"75890","Fstatus":"1","Fvid":"k0090OSAaO0"}},{"Flisten_count1":0,"Fupload_time":"2013-05-09 11:10:53","index":13,"isnew":0,"listenCount":0,"musicData":{"albumdesc":"《光辉岁月》电影主题曲","albumid":779701,"albummid":"003YLlz83XAfDI","albumname":"光辉岁月","alertid":11,"belongCD":1,"cdIdx":0,"interval":241,"isonly":0,"label":"4611686018435776514","msgid":0,"pay":{"payalbum":0,"payalbumprice":0,"paydownload":0,"payinfo":0,"payplay":0,"paytrackmouth":0,"paytrackprice":0,"timefree":0},"preview":{"trybegin":0,"tryend":0,"trysize":0},"rate":7,"singer":[{"id":143,"mid":"003Nz2So3XXYek","name":"陈奕迅"}],"size128":3868828,"size320":9671745,"size5_1":0,"sizeape":0,"sizeflac":0,"sizeogg":5455150,"songid":4816947,"songmid":"0022lGNw3Zhs1w","songname":"光辉岁月","songorig":"光辉岁月","songtype":0,"strMediaMid":"0022lGNw3Zhs1w","stream":13,"switch":3227447,"type":0,"vid":""},"playurl":"","price":320,"vid":null},{"Flisten_count1":0,"Fupload_time":"2012-04-09 18:20:38","index":14,"isnew":0,"listenCount":0,"musicData":{"albumdesc":"《将爱情进行到底》电影主题曲","albumid":103805,"albummid":"000xEWk64FUfLe","albumname":"等你爱我","alertid":21,"belongCD":1,"cdIdx":0,"interval":283,"isonly":1,"label":"4611686153727246337","msgid":14,"pay":{"payalbum":0,"payalbumprice":0,"paydownload":1,"payinfo":1,"payplay":0,"paytrackmouth":1,"paytrackprice":200,"timefree":0},"preview":{"trybegin":0,"tryend":0,"trysize":0},"rate":23,"singer":[{"id":143,"mid":"003Nz2So3XXYek","name":"陈奕迅"}],"size128":4540488,"size320":11350924,"size5_1":0,"sizeape":0,"sizeflac":25393962,"sizeogg":5756536,"songid":1248227,"songmid":"001SColy043UDM","songname":"等你爱我","songorig":"等你爱我","songtype":0,"strMediaMid":"003yqRqE45Q5NO","stream":13,"switch":17413891,"type":0,"vid":"n00121xukg8"},"playurl":"","price":320,"vid":{"Fmv_id":"198122","Fstatus":"1","Fvid":"n00121xukg8"}},{"Flisten_count1":0,"Fupload_time":"2015-04-30 16:47:46","index":15,"isnew":0,"listenCount":0,"musicData":{"albumdesc":"","albumid":13118,"albummid":"0040p89Y14npr4","albumname":"婚礼的祝福","alertid":2,"belongCD":1,"cdIdx":0,"interval":261,"isonly":0,"label":"4611686018431582209","msgid":14,"pay":{"payalbum":0,"payalbumprice":0,"paydownload":1,"payinfo":1,"payplay":0,"paytrackmouth":1,"paytrackprice":200,"timefree":0},"preview":{"trybegin":0,"tryend":0,"trysize":0},"rate":31,"singer":[{"id":143,"mid":"003Nz2So3XXYek","name":"陈奕迅"}],"size128":4191496,"size320":10478438,"size5_1":0,"sizeape":26534973,"sizeflac":26713613,"sizeogg":5777643,"songid":102376312,"songmid":"001LUMva0LbQrE","songname":"婚礼的祝福","songorig":"婚礼的祝福","songtype":0,"strMediaMid":"001LUMva0LbQrE","stream":13,"switch":17413891,"type":0,"vid":"a0010IsRxEQ"},"playurl":"","price":320,"vid":{"Fmv_id":"119430","Fstatus":"1","Fvid":"a0010IsRxEQ"}},{"Flisten_count1":0,"Fupload_time":"2012-05-24 15:43:51","index":16,"isnew":0,"listenCount":0,"musicData":{"albumdesc":"","albumid":114589,"albummid":"001ZLjzB19w316","albumname":"ReImagine Leslie Cheung","alertid":21,"belongCD":9,"cdIdx":0,"interval":263,"isonly":1,"label":"4611686153727246338","msgid":14,"pay":{"payalbum":0,"payalbumprice":0,"paydownload":1,"payinfo":1,"payplay":0,"paytrackmouth":1,"paytrackprice":200,"timefree":0},"preview":{"trybegin":0,"tryend":0,"trysize":0},"rate":23,"singer":[{"id":143,"mid":"003Nz2So3XXYek","name":"陈奕迅"}],"size128":4209503,"size320":10523403,"size5_1":0,"sizeape":0,"sizeflac":26693773,"sizeogg":5664809,"songid":1410008,"songmid":"004NWb2e2HENE9","songname":"最冷一天","songorig":"最冷一天","songtype":0,"strMediaMid":"001ghh2i06yEfM","stream":13,"switch":17413891,"type":0,"vid":""},"playurl":"","price":320,"vid":null},{"Flisten_count1":0,"Fupload_time":"2012-04-12 19:49:17","index":17,"isnew":0,"listenCount":0,"musicData":{"albumdesc":"","albumid":38111,"albummid":"0022CVkS4GIYsQ","albumname":"H³M","alertid":21,"belongCD":3,"cdIdx":0,"interval":238,"isonly":1,"label":"4611686018431582210","msgid":14,"pay":{"payalbum":0,"payalbumprice":0,"paydownload":1,"payinfo":1,"payplay":0,"paytrackmouth":1,"paytrackprice":200,"timefree":0},"preview":{"trybegin":0,"tryend":0,"trysize":0},"rate":23,"singer":[{"id":143,"mid":"003Nz2So3XXYek","name":"陈奕迅"}],"size128":3810311,"size320":9525485,"size5_1":0,"sizeape":0,"sizeflac":24793617,"sizeogg":4986550,"songid":1260806,"songmid":"004SmM9I1NwSbk","songname":"于心有愧","songorig":"于心有愧","songtype":0,"strMediaMid":"003K98eP0GxTK0","stream":13,"switch":17413891,"type":0,"vid":"u0011dqpew1"},"playurl":"","price":320,"vid":{"Fmv_id":"167268","Fstatus":"1","Fvid":"u0011dqpew1"}},{"Flisten_count1":0,"Fupload_time":"2012-04-28 11:22:29","index":18,"isnew":0,"listenCount":0,"musicData":{"albumdesc":"","albumid":8442,"albummid":"002FT46H18G1jW","albumname":"Life Continues…","alertid":21,"belongCD":5,"cdIdx":0,"interval":237,"isonly":1,"label":"4611686153723052034","msgid":14,"pay":{"payalbum":0,"payalbumprice":0,"paydownload":1,"payinfo":1,"payplay":0,"paytrackmouth":1,"paytrackprice":200,"timefree":0},"preview":{"trybegin":0,"tryend":0,"trysize":0},"rate":23,"singer":[{"id":143,"mid":"003Nz2So3XXYek","name":"陈奕迅"}],"size128":3801976,"size320":9504069,"size5_1":0,"sizeape":0,"sizeflac":26566430,"sizeogg":5297748,"songid":1338416,"songmid":"003pQhFw0oBP5p","songname":"落花流水","songorig":"落花流水","songtype":0,"strMediaMid":"002tZ4ij1AVME9","stream":13,"switch":17413891,"type":0,"vid":"q0012k9obcx"},"playurl":"","price":320,"vid":{"Fmv_id":"218513","Fstatus":"1","Fvid":"q0012k9obcx"}},{"Flisten_count1":0,"Fupload_time":"2011-12-11 18:00:55","index":19,"isnew":0,"listenCount":0,"musicData":{"albumdesc":"","albumid":89552,"albummid":"004S8YQr3UmEbG","albumname":"Shall We Dance? Shall We Talk!","alertid":21,"belongCD":3,"cdIdx":0,"interval":227,"isonly":1,"label":"4611686153727246338","msgid":14,"pay":{"payalbum":0,"payalbumprice":0,"paydownload":1,"payinfo":1,"payplay":0,"paytrackmouth":1,"paytrackprice":200,"timefree":0},"preview":{"trybegin":0,"tryend":0,"trysize":0},"rate":31,"singer":[{"id":143,"mid":"003Nz2So3XXYek","name":"陈奕迅"}],"size128":3637045,"size320":9120046,"size5_1":0,"sizeape":21683269,"sizeflac":22634568,"sizeogg":4900428,"songid":1050043,"songmid":"003OGTD62x8QrT","songname":"Shall We Talk","songorig":"Shall We Talk","songtype":0,"strMediaMid":"0033LU4F1pESxF","stream":13,"switch":17413891,"type":0,"vid":"v0011qlwan9"},"playurl":"","price":320,"vid":{"Fmv_id":"156787","Fstatus":"1","Fvid":"v0011qlwan9"}},{"Flisten_count1":0,"Fupload_time":"2016-06-13 16:31:03","index":20,"isnew":0,"listenCount":0,"musicData":{"albumdesc":"《大鱼海棠》动画电影主题曲","albumid":1475047,"albummid":"004dMsxC4gNo5U","albumname":"在这个世界相遇","alertid":21,"belongCD":1,"cdIdx":0,"interval":309,"isonly":1,"label":"4611686153727246337","msgid":14,"pay":{"payalbum":1,"payalbumprice":200,"paydownload":1,"payinfo":1,"payplay":0,"paytrackmouth":1,"paytrackprice":200,"timefree":0},"preview":{"trybegin":0,"tryend":0,"trysize":0},"rate":31,"singer":[{"id":143,"mid":"003Nz2So3XXYek","name":"陈奕迅"}],"size128":4951354,"size320":12378071,"size5_1":0,"sizeape":29733427,"sizeflac":29918946,"sizeogg":6489088,"songid":107313735,"songmid":"0001SFzi02ZZgb","songname":"在这个世界相遇","songorig":"在这个世界相遇","songtype":0,"strMediaMid":"0028xsVd0ijETa","stream":13,"switch":17413891,"type":0,"vid":"b0020gc1yej"},"playurl":"","price":320,"vid":{"Fmv_id":"752080","Fstatus":"1","Fvid":"b0020gc1yej"}},{"Flisten_count1":0,"Fupload_time":"2013-06-20 21:05:29","index":21,"isnew":0,"listenCount":0,"musicData":{"albumdesc":"《魂魄唔齐》插曲","albumid":89548,"albummid":"003yuBdQ0Vmcub","albumname":"The Line-Up","alertid":21,"belongCD":7,"cdIdx":0,"interval":230,"isonly":1,"label":"4611686018431582210","msgid":14,"pay":{"payalbum":0,"payalbumprice":0,"paydownload":1,"payinfo":1,"payplay":0,"paytrackmouth":1,"paytrackprice":200,"timefree":0},"preview":{"trybegin":79381,"tryend":116861,"trysize":0},"rate":31,"singer":[{"id":143,"mid":"003Nz2So3XXYek","name":"陈奕迅"}],"size128":3684104,"size320":9209942,"size5_1":0,"sizeape":24588854,"sizeflac":24707634,"sizeogg":5184137,"songid":4907858,"songmid":"001MzU812PDvbd","songname":"1874","songorig":"1874","songtype":0,"strMediaMid":"001MzU812PDvbd","stream":13,"switch":17413891,"type":0,"vid":"l0012pjsezg"},"playurl":"","price":320,"vid":{"Fmv_id":"206234","Fstatus":"1","Fvid":"l0012pjsezg"}},{"Flisten_count1":0,"Fupload_time":"2012-09-04 18:02:00","index":22,"isnew":0,"listenCount":0,"musicData":{"albumdesc":"","albumid":56098,"albummid":"001sjRhH0wqa4Q","albumname":"Time Flies","alertid":21,"belongCD":4,"cdIdx":0,"interval":278,"isonly":1,"label":"4611686153727246338","msgid":14,"pay":{"payalbum":0,"payalbumprice":0,"paydownload":1,"payinfo":1,"payplay":0,"paytrackmouth":1,"paytrackprice":200,"timefree":0},"preview":{"trybegin":0,"tryend":0,"trysize":0},"rate":23,"singer":[{"id":143,"mid":"003Nz2So3XXYek","name":"陈奕迅"}],"size128":4451473,"size320":11128307,"size5_1":0,"sizeape":0,"sizeflac":25790104,"sizeogg":5914920,"songid":1843622,"songmid":"002DuX1l4ddL5I","songname":"陀飞轮","songorig":"陀飞轮","songtype":0,"strMediaMid":"002MpZ1P0JF6hc","stream":13,"switch":17413891,"type":0,"vid":"E0010i2vkrV"},"playurl":"","price":320,"vid":{"Fmv_id":"140643","Fstatus":"1","Fvid":"E0010i2vkrV"}},{"Flisten_count1":0,"Fupload_time":"2012-04-27 17:18:57","index":23,"isnew":0,"listenCount":0,"musicData":{"albumdesc":"","albumid":8283,"albummid":"002E3o4u0kMw5s","albumname":"怎么样","alertid":21,"belongCD":2,"cdIdx":0,"interval":261,"isonly":1,"label":"4611686153718857729","msgid":14,"pay":{"payalbum":0,"payalbumprice":0,"paydownload":1,"payinfo":1,"payplay":0,"paytrackmouth":1,"paytrackprice":200,"timefree":0},"preview":{"trybegin":0,"tryend":0,"trysize":0},"rate":23,"singer":[{"id":143,"mid":"003Nz2So3XXYek","name":"陈奕迅"}],"size128":4190658,"size320":10476347,"size5_1":0,"sizeape":0,"sizeflac":29557825,"sizeogg":5722242,"songid":1334935,"songmid":"001v1h644TPK19","songname":"对不起 谢谢","songorig":"对不起 谢谢","songtype":0,"strMediaMid":"002eSCdi1qD9UX","stream":13,"switch":17413891,"type":0,"vid":"9dDqCgo4sfZ"},"playurl":"","price":320,"vid":{"Fmv_id":"77925","Fstatus":"1","Fvid":"9dDqCgo4sfZ"}},{"Flisten_count1":0,"Fupload_time":"2012-09-03 15:30:47","index":24,"isnew":0,"listenCount":0,"musicData":{"albumdesc":"浙江卫视台歌","albumid":1067277,"albummid":"004NALy80ppf4R","albumname":"梦想天空分外蓝","alertid":11,"belongCD":1,"cdIdx":0,"interval":200,"isonly":0,"label":"4611686018444165121","msgid":0,"pay":{"payalbum":0,"payalbumprice":0,"paydownload":0,"payinfo":0,"payplay":0,"paytrackmouth":0,"paytrackprice":0,"timefree":0},"preview":{"trybegin":0,"tryend":0,"trysize":0},"rate":7,"singer":[{"id":143,"mid":"003Nz2So3XXYek","name":"陈奕迅"}],"size128":3206792,"size320":8016667,"size5_1":0,"sizeape":0,"sizeflac":0,"sizeogg":3812341,"songid":1839561,"songmid":"000z2oXY18Hsli","songname":"梦想天空分外蓝","songorig":"梦想天空分外蓝","songtype":0,"strMediaMid":"002odgb51WyiaC","stream":13,"switch":3751735,"type":0,"vid":"x0011e218zx"},"playurl":"","price":320,"vid":{"Fmv_id":"145103","Fstatus":"1","Fvid":"x0011e218zx"}},{"Flisten_count1":0,"Fupload_time":"2010-06-29 15:31:30","index":25,"isnew":0,"listenCount":0,"musicData":{"albumdesc":"","albumid":58757,"albummid":"002gBayj0ZPoR0","albumname":"DUO 陈奕迅2010演唱会","alertid":21,"belongCD":4,"cdIdx":0,"interval":267,"isonly":1,"label":"4611686018431582210","msgid":14,"pay":{"payalbum":0,"payalbumprice":0,"paydownload":1,"payinfo":1,"payplay":0,"paytrackmouth":1,"paytrackprice":200,"timefree":0},"preview":{"trybegin":0,"tryend":0,"trysize":0},"rate":23,"singer":[{"id":143,"mid":"003Nz2So3XXYek","name":"陈奕迅"}],"size128":4282207,"size320":10704921,"size5_1":0,"sizeape":0,"sizeflac":27621249,"sizeogg":5801847,"songid":694532,"songmid":"003JGrp63AvAya","songname":"喜帖街 (Live)","songorig":"喜帖街","songtype":0,"strMediaMid":"0009U5eV1zmvmg","stream":13,"switch":17413891,"type":0,"vid":"w0022ag76j6"},"playurl":"","price":320,"vid":{"Fmv_id":"1085433","Fstatus":"1","Fvid":"w0022ag76j6"}},{"Flisten_count1":0,"Fupload_time":"2015-09-07 13:41:58","index":26,"isnew":0,"listenCount":0,"musicData":{"albumdesc":"","albumid":1135408,"albummid":"001BAQzm3y87AT","albumname":"无条件唱陈奕迅","alertid":21,"belongCD":1,"cdIdx":0,"interval":267,"isonly":1,"label":"4611686153727246338","msgid":14,"pay":{"payalbum":0,"payalbumprice":0,"paydownload":1,"payinfo":1,"payplay":0,"paytrackmouth":1,"paytrackprice":200,"timefree":0},"preview":{"trybegin":0,"tryend":0,"trysize":0},"rate":1,"singer":[{"id":143,"mid":"003Nz2So3XXYek","name":"陈奕迅"}],"size128":4283011,"size320":0,"size5_1":0,"sizeape":0,"sizeflac":0,"sizeogg":0,"songid":104113088,"songmid":"000rFZ6P3j46OD","songname":"无条件 (Live 2015)","songorig":"无条件","songtype":0,"strMediaMid":"000rFZ6P3j46OD","stream":13,"switch":17413891,"type":0,"vid":""},"playurl":"","price":320,"vid":{"Fstatus":null}},{"Flisten_count1":0,"Fupload_time":"2012-04-10 11:37:48","index":27,"isnew":0,"listenCount":0,"musicData":{"albumdesc":"","albumid":51144,"albummid":"003nMzes28P7wv","albumname":"What's Going On…?","alertid":21,"belongCD":1,"cdIdx":0,"interval":264,"isonly":1,"label":"4611686153727246338","msgid":14,"pay":{"payalbum":0,"payalbumprice":0,"paydownload":1,"payinfo":1,"payplay":0,"paytrackmouth":1,"paytrackprice":200,"timefree":0},"preview":{"trybegin":0,"tryend":0,"trysize":0},"rate":23,"singer":[{"id":143,"mid":"003Nz2So3XXYek","name":"陈奕迅"}],"size128":4233314,"size320":10582950,"size5_1":0,"sizeape":0,"sizeflac":31718009,"sizeogg":5860603,"songid":1249546,"songmid":"001WB1Un3SPiWp","songname":"裙下之臣","songorig":"裙下之臣","songtype":0,"strMediaMid":"004BupPO1VHVTh","stream":13,"switch":17413891,"type":0,"vid":""},"playurl":"","price":320,"vid":null},{"Flisten_count1":0,"Fupload_time":"2012-04-23 16:13:19","index":28,"isnew":0,"listenCount":0,"musicData":{"albumdesc":"《裙下之臣》国语版","albumid":31526,"albummid":"003yQidc3s7P65","albumname":"认了吧","alertid":21,"belongCD":1,"cdIdx":0,"interval":263,"isonly":1,"label":"4611686018427387905","msgid":14,"pay":{"payalbum":0,"payalbumprice":0,"paydownload":1,"payinfo":1,"payplay":0,"paytrackmouth":1,"paytrackprice":200,"timefree":0},"preview":{"trybegin":0,"tryend":0,"trysize":0},"rate":23,"singer":[{"id":143,"mid":"003Nz2So3XXYek","name":"陈奕迅"}],"size128":4214892,"size320":10536784,"size5_1":0,"sizeape":0,"sizeflac":31432891,"sizeogg":5756471,"songid":1313987,"songmid":"004RzMHU2QYv3Y","songname":"烟味","songorig":"烟味","songtype":0,"strMediaMid":"00384mCj1pjCfw","stream":13,"switch":17413891,"type":0,"vid":""},"playurl":"","price":320,"vid":{"Fstatus":null}},{"Flisten_count1":0,"Fupload_time":"2015-11-10 10:22:05","index":29,"isnew":0,"listenCount":0,"musicData":{"albumdesc":"《陪安东尼度过漫长岁月》电影英文主题曲|《陪你度过漫长岁月》英文版","albumid":1198389,"albummid":"0041kwqW2zFapr","albumname":"Sleep Alone","alertid":21,"belongCD":1,"cdIdx":0,"interval":145,"isonly":1,"label":"4611686018435776528","msgid":14,"pay":{"payalbum":0,"payalbumprice":0,"paydownload":1,"payinfo":1,"payplay":0,"paytrackmouth":1,"paytrackprice":200,"timefree":0},"preview":{"trybegin":41149,"tryend":80737,"trysize":0},"rate":7,"singer":[{"id":143,"mid":"003Nz2So3XXYek","name":"陈奕迅"}],"size128":2328812,"size320":5821147,"size5_1":0,"sizeape":0,"sizeflac":0,"sizeogg":3292509,"songid":104931761,"songmid":"0036tNSh39TvVB","songname":"Sleep Alone (英语)","songorig":"Sleep Alone","songtype":0,"strMediaMid":"0036tNSh39TvVB","stream":13,"switch":17413891,"type":0,"vid":"g00181eeb6m"},"playurl":"","price":320,"vid":{"Fmv_id":"657949","Fstatus":"1","Fvid":"g00181eeb6m"}},{"Flisten_count1":0,"Fupload_time":"2012-04-10 16:04:23","index":30,"isnew":0,"listenCount":0,"musicData":{"albumdesc":"","albumid":7879,"albummid":"003J6fvc0bVJon","albumname":"U-87","alertid":21,"belongCD":3,"cdIdx":0,"interval":244,"isonly":1,"label":"4611686153727246338","msgid":14,"pay":{"payalbum":0,"payalbumprice":0,"paydownload":1,"payinfo":1,"payplay":0,"paytrackmouth":1,"paytrackprice":200,"timefree":0},"preview":{"trybegin":0,"tryend":0,"trysize":0},"rate":23,"singer":[{"id":143,"mid":"003Nz2So3XXYek","name":"陈奕迅"}],"size128":3909372,"size320":9773130,"size5_1":0,"sizeape":0,"sizeflac":28710525,"sizeogg":5789051,"songid":1251164,"songmid":"000YQ7EJ27tZBf","songname":"夕阳无限好","songorig":"夕阳无限好","songtype":0,"strMediaMid":"003ONpGB35sjXN","stream":13,"switch":17413891,"type":0,"vid":"W0010niz0SZ"},"playurl":"","price":320,"vid":{"Fmv_id":"140637","Fstatus":"1","Fvid":"W0010niz0SZ"}}],"singer_id":"143","singer_mid":"003Nz2So3XXYek","singer_name":"陈奕迅","total":1391},"message":"succ","subcode":0}
